.tmuxp.yaml
CHANGES
LICENSE
MANIFEST.in
README.rst
setup.cfg
setup.py
doc/about.rst
doc/api.rst
doc/history.rst
doc/index.rst
examples/__init__.py
examples/flask_todo/__init__.py
examples/flask_todo/app.py
examples/flask_todo/models.py
flask_mongo_profiler/__about__.py
flask_mongo_profiler/__init__.py
flask_mongo_profiler/_compat.py
flask_mongo_profiler/constants.py
flask_mongo_profiler/helpers.py
flask_mongo_profiler/utils.py
flask_mongo_profiler.egg-info/PKG-INFO
flask_mongo_profiler.egg-info/SOURCES.txt
flask_mongo_profiler.egg-info/dependency_links.txt
flask_mongo_profiler.egg-info/not-zip-safe
flask_mongo_profiler.egg-info/requires.txt
flask_mongo_profiler.egg-info/top_level.txt
flask_mongo_profiler/contrib/__init__.py
flask_mongo_profiler/contrib/flask_admin/__init__.py
flask_mongo_profiler/contrib/flask_admin/helpers.py
flask_mongo_profiler/contrib/flask_admin/formatters/__init__.py
flask_mongo_profiler/contrib/flask_admin/formatters/date.py
flask_mongo_profiler/contrib/flask_admin/formatters/lookup.py
flask_mongo_profiler/contrib/flask_admin/formatters/polymorphic_relations.py
flask_mongo_profiler/contrib/flask_admin/formatters/profiling.py
flask_mongo_profiler/contrib/flask_admin/formatters/relational.py
flask_mongo_profiler/contrib/flask_admin/views/__init__.py
flask_mongo_profiler/contrib/flask_admin/views/base.py
flask_mongo_profiler/contrib/flask_admin/views/date.py
flask_mongo_profiler/contrib/flask_admin/views/profiling.py
flask_mongo_profiler/contrib/mongoengine/__init__.py
flask_mongo_profiler/contrib/mongoengine/mixins.py
flask_mongo_profiler/contrib/mongoengine/profiling.py
flask_mongo_profiler/contrib/werkzeug/__init__.py
flask_mongo_profiler/contrib/werkzeug/mongo.py
flask_mongo_profiler/contrib/werkzeug/werkzeug_middleware.py
requirements/base.txt
requirements/contrib.txt
requirements/dev.txt
requirements/doc.txt
requirements/test.txt
tests/__init__.py
tests/test_examples.py