Metadata-Version: 1.1
Name: flask-mongo-profiler
Version: 0.5.0a3.post0
Summary: Profiling tools for MongoDB
Home-page: https://github.com/peergradeio/flask-mongo-profiler
Author: Peergrade
Author-email: team@peergrade.io
License: MIT
Download-URL: https://pypi.org/project/flask-mongo-profiler/
Keywords: flask-mongo-profiler
Platform: UNKNOWN
Classifier: Development Status :: 5 - Production/Stable
Classifier: License :: OSI Approved :: MIT License
Classifier: Operating System :: POSIX
Classifier: Operating System :: MacOS :: MacOS X
Classifier: Environment :: Web Environment
Classifier: Intended Audience :: Developers
Classifier: Programming Language :: Python
Classifier: Programming Language :: Python :: 2.7
Classifier: Programming Language :: Python :: 3.5
Classifier: Programming Language :: Python :: 3.6
Classifier: Programming Language :: Python :: Implementation :: PyPy
Classifier: Topic :: Utilities
